FortiGateConverter-0.1.0.dist-info/DESCRIPTION.rst
FortiGateConverter-0.1.0.dist-info/METADATA
FortiGateConverter-0.1.0.dist-info/RECORD
FortiGateConverter-0.1.0.dist-info/WHEEL
FortiGateConverter-0.1.0.dist-info/metadata.json
FortiGateConverter-0.1.0.dist-info/top_level.txt
fortigateconverter/__init__.py
fortigateconverter/apps.py
fortigateconverter/models.py
fortigateconverter/urls.py
fortigateconverter/views.py
fortigateconverter/static/css/fortigateconverter.css
fortigateconverter/static/js/fortigateconverter.js
fortigateconverter/templates/fortigateconverter/base.html
