Metadata-Version: 2.0
Name: FortiGateConverter
Version: 0.1.0
Summary: Help to migrate configuration between FGTs.
Home-page: https://github.com/zhangdunxing/FortiGateConverter
Author: Dunxing Zhang
Author-email: dunxingzhang@fortinet.com
License: UNKNOWN
Keywords: FortiGateConverter
Platform: UNKNOWN
Classifier: Development Status :: 3 - Alpha
Classifier: Framework :: Django
Classifier: Framework :: Django :: 1.10
Classifier: Intended Audience :: Developers
Classifier: License :: OSI Approved :: BSD License
Classifier: Natural Language :: English
Classifier: Programming Language :: Python :: 2
Classifier: Programming Language :: Python :: 2.7
Classifier: Programming Language :: Python :: 3
Classifier: Programming Language :: Python :: 3.4
Classifier: Programming Language :: Python :: 3.5
